academia_tts/__init__.py
academia_tts/tts.py
academia_tts/scripts/__init__.py
academia_tts/scripts/tts_output_wav.py
academia_tts/scripts/tts_pptx.py
academia_tts-0.2.4.dist-info/METADATA
academia_tts-0.2.4.dist-info/WHEEL
academia_tts-0.2.4.dist-info/entry_points.txt
academia_tts-0.2.4.dist-info/top_level.txt
academia_tts-0.2.4.dist-info/RECORD
